chuk_mcp_runtime/__init__.py
chuk_mcp_runtime/entry.py
chuk_mcp_runtime/main.py
chuk_mcp_runtime/proxy_cli.py
chuk_mcp_runtime/types.py
chuk_mcp_runtime/artifacts/__init__.py
chuk_mcp_runtime/common/__init__.py
chuk_mcp_runtime/common/errors.py
chuk_mcp_runtime/common/mcp_resource_decorator.py
chuk_mcp_runtime/common/mcp_tool_decorator.py
chuk_mcp_runtime/common/openai_compatibility.py
chuk_mcp_runtime/common/tool_naming.py
chuk_mcp_runtime/common/verify_credentials.py
chuk_mcp_runtime/grid/hub_sandbox.py
chuk_mcp_runtime/proxy/__init__.py
chuk_mcp_runtime/proxy/manager.py
chuk_mcp_runtime/proxy/tool_wrapper.py
chuk_mcp_runtime/server/__init__.py
chuk_mcp_runtime/server/config_loader.py
chuk_mcp_runtime/server/event_store.py
chuk_mcp_runtime/server/logging_config.py
chuk_mcp_runtime/server/request_context.py
chuk_mcp_runtime/server/server.py
chuk_mcp_runtime/server/server_registry.py
chuk_mcp_runtime/session/__init__.py
chuk_mcp_runtime/session/native_session_management.py
chuk_mcp_runtime/session/session_management.py
chuk_mcp_runtime/tools/__init__.py
chuk_mcp_runtime/tools/artifacts_tools.py
chuk_mcp_runtime/tools/session_tools.py
chuk_mcp_runtime-0.10.8.dist-info/METADATA
chuk_mcp_runtime-0.10.8.dist-info/WHEEL
chuk_mcp_runtime-0.10.8.dist-info/entry_points.txt
chuk_mcp_runtime-0.10.8.dist-info/top_level.txt
chuk_mcp_runtime-0.10.8.dist-info/RECORD
