Metadata-Version: 2.4
Name: chuk-mcp-runtime
Version: 0.10.8
Summary: Generic CHUK MCP Runtime for MCP servers
Author-email: Chris Hay <your.email@example.com>
License: MIT
Requires-Python: >=3.11
Requires-Dist: pydantic>=2.10.6
Requires-Dist: pyyaml>=6.0.2
Requires-Dist: pyjwt>=2.10.1
Requires-Dist: cryptography>=44.0.3
Requires-Dist: uvicorn>=0.34.0
Requires-Dist: chuk-artifacts>=0.10.1
Requires-Dist: chuk-sessions>=0.6
Requires-Dist: mcp>=1.23.0
Provides-Extra: dev
Requires-Dist: pytest>=8.3.5; extra == "dev"
Requires-Dist: pytest-asyncio>=0.23.0; extra == "dev"
Requires-Dist: pytest-cov>=6.0.0; extra == "dev"
Requires-Dist: ruff>=0.4.6; extra == "dev"
Requires-Dist: mypy>=1.13.0; extra == "dev"
Requires-Dist: bandit>=1.7.0; extra == "dev"
Provides-Extra: websocket
Requires-Dist: websockets>=14.1; extra == "websocket"
